proxyprefix/__init__.py
proxyprefix/wsgi.py
proxyprefix/contrib/__init__.py
proxyprefix/contrib/djproxy.py
proxyprefix-0.1.2.dist-info/DESCRIPTION.rst
proxyprefix-0.1.2.dist-info/METADATA
proxyprefix-0.1.2.dist-info/RECORD
proxyprefix-0.1.2.dist-info/WHEEL
proxyprefix-0.1.2.dist-info/metadata.json
proxyprefix-0.1.2.dist-info/top_level.txt
