Metadata-Version: 2.0
Name: proxyprefix
Version: 0.1.2
Summary: Prefix SCRIPT_NAME with X-Forwarded-Prefix header
Home-page: https://github.com/yola/proxyprefix
Author: Yola
Author-email: engineers@yola.com
License: MIT (Expat)
Platform: UNKNOWN
Classifier: License :: OSI Approved :: MIT License
Classifier: Programming Language :: Python :: 2
Classifier: Topic :: Internet :: WWW/HTTP :: WSGI :: Middleware
Provides-Extra: djproxy
Requires-Dist: djproxy (>=2.0.0); extra == 'djproxy'
